<?xml version="1.0" ?>
<!DOCTYPE PISI SYSTEM "http://www.pisilinux.org/projeler/pisi/pisi-spec.dtd">
<PISI>
    <Source>
        <Name>FusionSound</Name>
        <Homepage>http://www.directfb.org</Homepage>
        <Packager>
            <Name>PisiLinux Community</Name>
            <Email>admins@pisilinux.org</Email>
        </Packager>
        <License>GPLv2</License>
        <IsA>library</IsA>
        <Summary>Sound library</Summary>
        <Description>Sound library part of the DirectFB project.</Description>
        <Archive sha1sum="cd5e45d5ab3d83b9474e8d4dc36a0b43e637f302" type="targz">http://www.directfb.org/downloads/Core/FusionSound/FusionSound-1.1.1.tar.gz</Archive>
        <BuildDependencies>
            <Dependency>libvorbis-devel</Dependency>
            <Dependency>alsa-lib-devel</Dependency>
            <Dependency>DirectFB-devel</Dependency>
            <Dependency>libcddb-devel</Dependency>
            <Dependency>libogg-devel</Dependency>
            <Dependency>libmad-devel</Dependency>
            <Dependency>ffmpeg-devel</Dependency>
            <Dependency>imlib2-devel</Dependency>
        </BuildDependencies>
        <Patches>
            <Patch level="0">FusionSound-1.1.1-gcc43.patch</Patch>
            <Patch level="1">FusionSound-1.1.1-ffmpeg.patch</Patch>
            <Patch level="0">FusionSound-1.1.1-ffmpeg-0.6.90.patch</Patch>
            <Patch level="1">FusionSound-1.1.1-ffmpeg-0.10.patch</Patch>
            <Patch level="1">FusionSound-1.1.1-libavformat54.patch</Patch>
            <Patch level="1">FusionSound-1.1.1-libav-0.8.1.patch</Patch>
            <Patch level="1">FusionSound-1.1.1-libav-9.patch</Patch>
        </Patches>
    </Source>

    <Package>
        <Name>FusionSound</Name>
        <RuntimeDependencies>
            <Dependency>libvorbis</Dependency>
            <Dependency>alsa-lib</Dependency>
            <Dependency>DirectFB</Dependency>
            <Dependency>libcddb</Dependency>
            <Dependency>libogg</Dependency>
            <Dependency>libmad</Dependency>
            <Dependency>ffmpeg</Dependency>
            <Dependency>imlib2</Dependency>
        </RuntimeDependencies>
        <Files>
            <Path fileType="executable">/usr/bin</Path>
            <Path fileType="library">/usr/lib</Path>
            <Path fileType="doc">/usr/share/doc</Path>
            <Path fileType="man">/usr/share/man</Path>
        </Files>
    </Package>

    <Package>
        <Name>FusionSound-devel</Name>
        <Summary>Development files for FusionSound</Summary>
        <RuntimeDependencies>
            <Dependency release="current">FusionSound</Dependency>
            <Dependency>DirectFB-devel</Dependency>
        </RuntimeDependencies>
        <Files>
            <Path fileType="header">/usr/include</Path>
            <Path fileType="doc">/usr/share/doc/FusionSound/html</Path>
            <Path fileType="data">/usr/lib/pkgconfig</Path>
        </Files>
    </Package>

    <History>
        <Update release="3">
            <Date>2013-08-29</Date>
            <Version>1.1.1</Version>
            <Comment>missing dep.</Comment>
            <Name>Erdinç gültekin</Name>
            <Email>erdincgultekin@pisilinux.org</Email>
        </Update>
        <Update release="2">
            <Date>2013-03-08</Date>
            <Version>1.1.1</Version>
            <Comment>V.Bump</Comment>
            <Name>Osman Erkan</Name>
            <Email>osman.erkan@pisilinux.org</Email>
        </Update>
        <Update release="1">
            <Date>2010-10-12</Date>
            <Version>0.0_20080311</Version>
            <Comment>First release</Comment>
            <Name>Pisi Linux Admins</Name>
            <Email>admins@pisilinux.org</Email>
        </Update>
    </History>
</PISI>