<?xml version="1.0" ?>
<!DOCTYPE PISI SYSTEM "http://www.pisilinux.org/projeler/pisi/pisi-spec.dtd">
<PISI>
    <Source>
        <Name>kopete</Name>
        <Homepage>http://kopete.kde.org/</Homepage>
        <Packager>
            <Name>Mathias Freire</Name>
            <Email>mathiasfreire45@gmail.com</Email>
        </Packager>
        <License>GPLv2</License>
        <Icon>kopete</Icon>
        <IsA>app:gui</IsA>
        <Summary>Instant messaging application for KDE</Summary>
        <Description>Kopete is an instant messenger supporting AIM, ICQ, Windows Live Messenger, Yahoo, Jabber, Gadu-Gadu, Novell GroupWise Messenger, and more.</Description>
        <Archive sha1sum="1dd677e6fd4335e6d0bb906f4c981395ca204e12" type="tarxz">mirrors://kde/stable/4.11.1/src/kopete-4.11.1.tar.xz</Archive>
        <BuildDependencies>
            <Dependency versionFrom="4.11.1">kdelibs-devel</Dependency>
            <Dependency versionFrom="4.11.1">kdepimlibs-devel</Dependency>
            <Dependency versionFrom="4.11.1">kde-runtime-devel</Dependency>
            <Dependency>libidn-devel</Dependency>
            <Dependency>jasper-devel</Dependency>
            <Dependency>qt-devel</Dependency>
            <Dependency>libmsn-devel</Dependency>
            <Dependency>phonon-devel</Dependency>
            <Dependency>qca2-devel</Dependency>
            <Dependency>qimageblitz-devel</Dependency>
            <Dependency>libotr-devel</Dependency>
            <Dependency>libgadu-devel</Dependency>
            <Dependency>ortp-devel</Dependency>
            <Dependency>mediastreamer2-devel</Dependency>
            <Dependency>libv4l-devel</Dependency>
            <Dependency>libjpeg-turbo-devel</Dependency>
            <Dependency>giflib-devel</Dependency>
            <Dependency>speex-devel</Dependency>
            <Dependency>libmms-devel</Dependency>
            <Dependency>meanwhile-devel</Dependency>
        </BuildDependencies>
    </Source>

    <Package>
        <Name>kopete</Name>
        <RuntimeDependencies>
            <Dependency versionFrom="4.11.1">kdelibs</Dependency>
            <Dependency versionFrom="4.11.1">kdepimlibs</Dependency>
            <Dependency versionFrom="4.11.1">kdepim</Dependency>
            <Dependency versionFrom="4.11.1">kdepim-runtime</Dependency>
            <Dependency versionFrom="4.11.1">kde-runtime</Dependency>
            <Dependency versionFrom="4.11.1">kdnssd</Dependency>
            <Dependency>libidn</Dependency>
            <Dependency>jasper</Dependency>
            <Dependency>qt</Dependency>
            <Dependency>libmsn</Dependency>
            <Dependency>phonon</Dependency>
            <Dependency>qca2</Dependency>
            <Dependency>qimageblitz</Dependency>
            <Dependency>libotr</Dependency>
            <Dependency>libgadu</Dependency> 
            <Dependency>ortp</Dependency> 
            <Dependency>mediastreamer2</Dependency>
            <Dependency>libv4l</Dependency>
            <Dependency>libjpeg-turbo</Dependency>
            <Dependency>giflib</Dependency>
            <Dependency>speex</Dependency>
            <Dependency>libmms</Dependency>
            <Dependency>meanwhile</Dependency>
            <Dependency>libxslt</Dependency>
            <Dependency>libXScrnSaver</Dependency> 
        </RuntimeDependencies>
        <Replaces>
            <Package>kdenetwork</Package>
        </Replaces>
        <Conflicts>
            <Package>kdenetwork</Package>
        </Conflicts>        
        <Files>
            <Path fileType="executable">/usr/bin</Path>
            <Path fileType="library">/usr/lib</Path>
            <Path fileType="data">/usr/share</Path> 
            <Path fileType="doc">/usr/share/doc</Path>
        </Files>
    </Package>
    
    <Package>
      <Name>kopete-devel</Name>
      <Summary>Devel files for Kopete</Summary>
        <RuntimeDependencies>
            <Dependency release="current">kopete</Dependency>
        </RuntimeDependencies>
        <Replaces>
            <Package>kdenetwork-devel</Package>
        </Replaces>
        <Files>
            <Path fileType="header">/usr/include</Path>            
        </Files>
    </Package>

    <History>
        <Update release="1">
            <Date>2013-09-03</Date>
            <Version>4.11.1</Version>
            <Comment>First release</Comment>
            <Name>Mathias Freire</Name>
            <Email>mathiasfreire45@gmail.com</Email>
        </Update>
    </History>
</PISI>
