<?xml version="1.0" ?>
<PISI>
    <Source>
        <Name>e-module-iiirk</Name>
        <Summary xml:lang="tr">Görev çubuğu benzeri modul</Summary>
        <Description xml:lang="tr">Sadece seçilen uygulamalar için görev çubuğu gibi davranan bir modüldür.</Description>
        <Summary xml:lang="nl">Iiirk module voor Enlightenment</Summary>
        <Description xml:lang="nl">E-module-iiirk, kan zich gedragen als een taakbalk voor geselecteerde toepassingen. Het doel is het hebben van een module die zich gedraagt als een iconen dock.</Description>
    </Source>
</PISI>

