<PISI>
    <Source>
        <Name>lxqt-panel</Name>
        <Homepage>http://www.lxde.org</Homepage>
        <Packager>
            <Name>Ayhan Yalçınsoy</Name>
            <Email>ayhanyalcinsoy@pisilinux.org</Email>
        </Packager>
        <License>GPL2</License>
        <IsA>app</IsA>
        <Summary>Desktop panel</Summary>
        <Description>The LXQt desktop panel</Description>
            <Archive sha1sum="b2d91a0d5139cb5f46b46f3125e441dd6430f876" type="targz">https://github.com/lxde/lxqt-panel/archive/0.8.0.tar.gz</Archive>
        <BuildDependencies>
            <Dependency>icu4c-devel</Dependency>
            <Dependency>liblxqt-devel</Dependency>
            <Dependency>gcc</Dependency>
            <Dependency>desktop-file-utils</Dependency>
            <Dependency>qt-devel</Dependency>
            <Dependency>liblxqt-mount-devel</Dependency>
            <Dependency>libqtxdg-devel</Dependency>
            <Dependency>libsysstat-devel</Dependency>
            <Dependency>lxqt-globalkeys-devel</Dependency>
            <Dependency>lxqt-menu-cache-devel</Dependency>
            <Dependency>pulseaudio-libs-devel</Dependency>
            <Dependency>alsa-lib-devel</Dependency>
            <Dependency>libXcomposite-devel</Dependency>
            <Dependency>lm_sensors-devel</Dependency>
            <Dependency>libxcb-devel</Dependency>
            <Dependency>network-manager-applet-devel</Dependency>
            <Dependency>libXcomposite-devel</Dependency>
            <Dependency>libstatgrab</Dependency>
            <Dependency>libX11-devel</Dependency>
        </BuildDependencies>
        </Source>
    <Package>
        <Name>lxqt-panel</Name>
        <RuntimeDependencies>
            <Dependency>icu4c</Dependency>
            <Dependency>libXdamage</Dependency>
            <Dependency>liblxqt-mount</Dependency>
            <Dependency>lxqt-globalkeys</Dependency>
            <Dependency>libsysstat</Dependency>
            <Dependency>alsa-lib</Dependency>
            <Dependency>pulseaudio-libs</Dependency>
            <Dependency>libXcomposite</Dependency>
            <Dependency>libXrender</Dependency>
            <Dependency>lm_sensors</Dependency>
            <Dependency>libstatgrab</Dependency>
            <Dependency>qt</Dependency>
            <Dependency>liblxqt</Dependency>
            <Dependency>libqtxdg</Dependency>
            <Dependency>qtmimetypes</Dependency>
            <Dependency>libmenu-cache</Dependency>
        </RuntimeDependencies>
        <Files>
            <Path fileType="executable">/usr/bin</Path>
            <Path fileType="library">/usr/lib</Path>
            <Path fileType="localedata">/usr/share/locale</Path>
            <Path fileType="man">/usr/share/man</Path>
            <Path fileType="doc">/usr/share/doc</Path>
            <Path fileType="data">/usr/share</Path>
            <Path fileType="config">/etc/lxqt</Path>
        </Files>
    </Package>
    <Package>
        <Name>lxqt-panel-devel</Name>
        <Summary>Development headers for lxqt-panel</Summary>
        <Files>
            <Path fileType="header">/usr/include</Path>
            <Path fileType="library">/usr/lib/pkgconfig</Path>
        </Files>
    </Package>
    <History>
        <Update release="2">
            <Date>2014-10-21</Date>
            <Version>0.8.0</Version>
            <Comment>version bump.</Comment>
            <Name>Ayhan Yalçınsoy</Name>
            <Email>ayhanyalcinsoy@pisilinux.org</Email>
        </Update>
        <Update release="1">
            <Date>2014-05-02</Date>
            <Version>0.7.0</Version>
            <Comment>First Release</Comment>
            <Name>Vedat Demir</Name>
            <Email>vedat@pisilinux.org</Email>
        </Update>
    </History>
</PISI>

