<?xml version="1.0" ?>
<PISI>
    <Source>
        <Name>wget</Name>
        <Summary xml:lang="tr">Http ve ftp gibi internet protokollerini kullanarak dosya indirebilen bir yazılım</Summary>
        <Description xml:lang="tr">GNU Wget, HTTP, HTTPS ve FTP gibi en çok kullanılan Internet protokollerini kullanarak dosyalara ulaşmak icin kullanılan bir özgür yazılım paketidir. Etkileşimsiz bir komutsatırı aracıdır, böylece X-Windows desteği olmadan, betikler, işlemler, terminal kullanımı gerçekleştirilebilir.</Description>
    </Source>
</PISI>
