<?xml version="1.0" ?>
<PISI>
    <Source>
        <Name>python-M2Crypto</Name>
        <Summary xml:lang="tr">Python Kripto ve SSL Araç Takımı</Summary>
        <Description xml:lang="tr">OpenSSL için Pythonla yazılmış en geniş ara yazılımdır(wrapper). RSA, DSA, DH, HMACs, mesaj özetleri, simetrik şifreleme (AES dahil); sunucular ve istemciler için SSL özelliği; Python'un httplib, urllib ve xmlrpclib kitaplıklarına HTTPS eklentileri, ağ oturum yönetimi için değiştirilemeyen HMAC'leyici AuthCookie'ler; FPT/TLS istemci ve sunucusu; S/MIME; ZServerSSL; Zope ve ZSmime için HTTPS sunucu; Zope için S/MIME habercisi(messenger) gibi özellikleri bulunmaktadır. M2crypto ayrıca Twisted için SSL desteği de sağlayabilir.</Description>
    </Source>
</PISI>
