<?xml version="1.0" ?>
<PISI>
    <Source>
        <Name>e-module-mem</Name>
        <Summary xml:lang="tr">Enlightenment için bellek izleme modulü</Summary>
        <Description xml:lang="tr">E-module-mem, Enlightenment için bir bellek gözlemleme modülüdür.</Description>
        <Summary xml:lang="nl">Geheugen-monitor module voor Enlightenment</Summary>
        <Description xml:lang="nl">E-module-mem is een geheugengebruik controle module voor Enlightenment.</Description>
    </Source>
</PISI>
